{
  "code": 0,
  "msg": "请求成功",
  "page": 1,
  "limit": 100,
  "count": 9,
  "data": [
    {
      "createTime": "2023-08-30 09:32:22",
      "createUser": "1265476890672672808",
      "updateTime": null,
      "updateUser": null,
      "id": "1696697336864186370",
      "codeGenId": "1696697336797077505",
      "columnName": "id",
      "javaName": "id",
      "columnComment": "id",
      "javaType": "Integer",
      "effectType": "input",
      "dictTypeCode": null,
      "whetherRetract": "N",
      "whetherRequired": "N",
      "queryWhether": "N",
      "queryType": "eq",
      "whetherTable": "N",
      "whetherAddUpdate": "N",
      "columnKey": "PRI",
      "columnKeyName": "Id",
      "dataType": "int",
      "whetherCommon": "N"
    },
    {
      "createTime": "2023-08-30 09:32:22",
      "createUser": "1265476890672672808",
      "updateTime": null,
      "updateUser": null,
      "id": "1696697336864186371",
      "codeGenId": "1696697336797077505",
      "columnName": "name",
      "javaName": "name",
      "columnComment": "名称",
      "javaType": "String",
      "effectType": "input",
      "dictTypeCode": null,
      "whetherRetract": "N",
      "whetherRequired": "Y",
      "queryWhether": "Y",
      "queryType": "eq",
      "whetherTable": "Y",
      "whetherAddUpdate": "Y",
      "columnKey": "",
      "columnKeyName": "Name",
      "dataType": "varchar",
      "whetherCommon": "N"
    },
    {
      "createTime": "2023-08-30 09:32:22",
      "createUser": "1265476890672672808",
      "updateTime": null,
      "updateUser": null,
      "id": "1696697336864186372",
      "codeGenId": "1696697336797077505",
      "columnName": "age",
      "javaName": "age",
      "columnComment": "年龄",
      "javaType": "Integer",
      "effectType": "input",
      "dictTypeCode": null,
      "whetherRetract": "N",
      "whetherRequired": "Y",
      "queryWhether": "Y",
      "queryType": "eq",
      "whetherTable": "Y",
      "whetherAddUpdate": "Y",
      "columnKey": "",
      "columnKeyName": "Age",
      "dataType": "int",
      "whetherCommon": "N"
    },
    {
      "createTime": "2023-08-30 09:32:22",
      "createUser": "1265476890672672808",
      "updateTime": null,
      "updateUser": null,
      "id": "1696697336931295233",
      "codeGenId": "1696697336797077505",
      "columnName": "status",
      "javaName": "status",
      "columnComment": "{\"name\":\"状态\",\"1\":\"启用\",\"0\":\"禁用\"}",
      "javaType": "Integer",
      "effectType": "input",
      "dictTypeCode": null,
      "whetherRetract": "N",
      "whetherRequired": "Y",
      "queryWhether": "Y",
      "queryType": "eq",
      "whetherTable": "Y",
      "whetherAddUpdate": "Y",
      "columnKey": "",
      "columnKeyName": "Status",
      "dataType": "int",
      "whetherCommon": "N"
    },
    {
      "createTime": "2023-08-30 09:32:22",
      "createUser": "1265476890672672808",
      "updateTime": null,
      "updateUser": null,
      "id": "1696697336931295234",
      "codeGenId": "1696697336797077505",
      "columnName": "birthday",
      "javaName": "birthday",
      "columnComment": "生日",
      "javaType": "Date",
      "effectType": "datepicker",
      "dictTypeCode": null,
      "whetherRetract": "N",
      "whetherRequired": "Y",
      "queryWhether": "Y",
      "queryType": "eq",
      "whetherTable": "Y",
      "whetherAddUpdate": "Y",
      "columnKey": "",
      "columnKeyName": "Birthday",
      "dataType": "date",
      "whetherCommon": "N"
    },
    {
      "createTime": "2023-08-30 09:32:22",
      "createUser": "1265476890672672808",
      "updateTime": null,
      "updateUser": null,
      "id": "1696697336998404097",
      "codeGenId": "1696697336797077505",
      "columnName": "remarks",
      "javaName": "remarks",
      "columnComment": "备注",
      "javaType": "String",
      "effectType": "input",
      "dictTypeCode": null,
      "whetherRetract": "N",
      "whetherRequired": "Y",
      "queryWhether": "Y",
      "queryType": "eq",
      "whetherTable": "Y",
      "whetherAddUpdate": "Y",
      "columnKey": "",
      "columnKeyName": "Remarks",
      "dataType": "text",
      "whetherCommon": "N"
    },
    {
      "createTime": "2023-08-30 09:32:22",
      "createUser": "1265476890672672808",
      "updateTime": null,
      "updateUser": null,
      "id": "1696697336998404098",
      "codeGenId": "1696697336797077505",
      "columnName": "mun",
      "javaName": "mun",
      "columnComment": "数字",
      "javaType": "BigDecimal",
      "effectType": "BigDecimal",
      "dictTypeCode": null,
      "whetherRetract": "N",
      "whetherRequired": "Y",
      "queryWhether": "Y",
      "queryType": "eq",
      "whetherTable": "Y",
      "whetherAddUpdate": "Y",
      "columnKey": "",
      "columnKeyName": "Mun",
      "dataType": "decimal",
      "whetherCommon": "N"
    },
    {
      "createTime": "2023-08-30 09:32:22",
      "createUser": "1265476890672672808",
      "updateTime": null,
      "updateUser": null,
      "id": "1696697336998404099",
      "codeGenId": "1696697336797077505",
      "columnName": "create_time",
      "javaName": "createTime",
      "columnComment": "创建时间",
      "javaType": "Date",
      "effectType": "datepicker",
      "dictTypeCode": null,
      "whetherRetract": "N",
      "whetherRequired": "N",
      "queryWhether": "N",
      "queryType": "eq",
      "whetherTable": "N",
      "whetherAddUpdate": "N",
      "columnKey": "",
      "columnKeyName": "CreateTime",
      "dataType": "datetime",
      "whetherCommon": "Y"
    },
    {
      "createTime": "2023-08-30 09:32:22",
      "createUser": "1265476890672672808",
      "updateTime": null,
      "updateUser": null,
      "id": "1696697337065512961",
      "codeGenId": "1696697336797077505",
      "columnName": "update_time",
      "javaName": "updateTime",
      "columnComment": "更新时间",
      "javaType": "Date",
      "effectType": "datepicker",
      "dictTypeCode": null,
      "whetherRetract": "N",
      "whetherRequired": "N",
      "queryWhether": "N",
      "queryType": "eq",
      "whetherTable": "N",
      "whetherAddUpdate": "N",
      "columnKey": "",
      "columnKeyName": "UpdateTime",
      "dataType": "datetime",
      "whetherCommon": "Y"
    }
  ]
}